windscangeo/__init__.py
windscangeo/func_goes.py
windscangeo/func_inference.py
windscangeo/func_ml.py
windscangeo/func_scatter.py
windscangeo/impl.py
windscangeo/models.py
windscangeo/utils.py
windscangeo/visualize.py
windscangeo-2025.1.dist-info/METADATA
windscangeo-2025.1.dist-info/WHEEL
windscangeo-2025.1.dist-info/licenses/LICENCE
windscangeo-2025.1.dist-info/RECORD
