Metadata-Version: 2.4
Name: windscangeo
Version: 2025.1
Summary: Easy extraction and processing of matching GOES geostationary satellite and polar orbiting scatterometer data for model training.
Project-URL: Homepage, https://windscangeo.github.io/
Author-email: Yongxing Loo  <yloo@tudelft.nl>
License-File: LICENCE
Classifier: License :: OSI Approved :: MIT License
Classifier: Operating System :: OS Independent
Classifier: Programming Language :: Python :: 3
Requires-Python: >=3.8
Requires-Dist: cartopy
Requires-Dist: fsspec
Requires-Dist: h5netcdf
Requires-Dist: h5py
Requires-Dist: matplotlib
Requires-Dist: netcdf4
Requires-Dist: numpy
Requires-Dist: pandas
Requires-Dist: s3fs
Requires-Dist: scikit-learn
Requires-Dist: torch
Requires-Dist: tqdm
Requires-Dist: xarray
